{"nodes": [{"id": "d_repos_shuuen_copy_bass_distrib_bass24_windows_delphi_contest_contest_dpr", "label": "ConTest.dpr", "file_type": "code", "source_file": "bass-distrib/bass24-windows/delphi/ConTest/ConTest.dpr", "source_location": "L1"}, {"id": "contest_contest_contest", "label": "ConTest", "file_type": "code", "source_file": "bass-distrib/bass24-windows/delphi/ConTest/ConTest.dpr", "source_location": "L1"}, {"id": "contest_contest_inttofixed", "label": "IntToFixed()", "file_type": "code", "source_file": "bass-distrib/bass24-windows/delphi/ConTest/ConTest.dpr", "source_location": "L11"}, {"id": "contest_contest_error", "label": "Error()", "file_type": "code", "source_file": "bass-distrib/bass24-windows/delphi/ConTest/ConTest.dpr", "source_location": "L21"}], "edges": [{"source": "d_repos_shuuen_copy_bass_distrib_bass24_windows_delphi_contest_contest_dpr", "target": "contest_contest_contest", "relation": "contains", "confidence": "EXTRACTED", "source_file": "bass-distrib/bass24-windows/delphi/ConTest/ConTest.dpr", "source_location": "L1", "weight": 1.0}, {"source": "contest_contest_contest", "target": "windows", "relation": "imports", "confidence": "EXTRACTED", "source_file": "bass-distrib/bass24-windows/delphi/ConTest/ConTest.dpr", "source_location": "L5", "weight": 1.0, "context": "import"}, {"source": "contest_contest_contest", "target": "sysutils", "relation": "imports", "confidence": "EXTRACTED", "source_file": "bass-distrib/bass24-windows/delphi/ConTest/ConTest.dpr", "source_location": "L5", "weight": 1.0, "context": "import"}, {"source": "contest_contest_contest", "target": "mmsystem", "relation": "imports", "confidence": "EXTRACTED", "source_file": "bass-distrib/bass24-windows/delphi/ConTest/ConTest.dpr", "source_location": "L5", "weight": 1.0, "context": "import"}, {"source": "contest_contest_contest", "target": "bass", "relation": "imports", "confidence": "EXTRACTED", "source_file": "bass-distrib/bass24-windows/delphi/ConTest/ConTest.dpr", "source_location": "L5", "weight": 1.0, "context": "import"}, {"source": "contest_contest_contest", "target": "contest_contest_inttofixed", "relation": "contains", "confidence": "EXTRACTED", "source_file": "bass-distrib/bass24-windows/delphi/ConTest/ConTest.dpr", "source_location": "L11", "weight": 1.0}, {"source": "contest_contest_contest", "target": "contest_contest_error", "relation": "contains", "confidence": "EXTRACTED", "source_file": "bass-distrib/bass24-windows/delphi/ConTest/ConTest.dpr", "source_location": "L21", "weight": 1.0}], "input_tokens": 0, "output_tokens": 0}